nemorosa/__init__.py
nemorosa/api.py
nemorosa/cli.py
nemorosa/client_instance.py
nemorosa/clients/__init__.py
nemorosa/clients/client_common.py
nemorosa/clients/deluge.py
nemorosa/clients/qbittorrent.py
nemorosa/clients/rtorrent.py
nemorosa/clients/scgitransport.py
nemorosa/clients/transmission.py
nemorosa/config.py
nemorosa/core.py
nemorosa/db.py
nemorosa/filecompare.py
nemorosa/filelinking.py
nemorosa/logger.py
nemorosa/main.py
nemorosa/scheduler.py
nemorosa/static/favicon.ico
nemorosa/static/nemorosa.svg
nemorosa/webserver.py
nemorosa-0.4.2.dist-info/WHEEL
nemorosa-0.4.2.dist-info/entry_points.txt
nemorosa-0.4.2.dist-info/METADATA
nemorosa-0.4.2.dist-info/RECORD
