Metadata-Version: 2.3
Name: nemorosa
Version: 0.4.2
Summary: A specialized cross-seeding tool designed for music torrents, featuring automatic file mapping, partial matching, and seamless torrent injection
Keywords: torrent,cross-seed
Author: KyokoMiki
License: GPL-3.0-or-later
Classifier: Development Status :: 4 - Beta
Classifier: License :: OSI Approved :: GNU General Public License v3 or later (GPLv3+)
Classifier: Operating System :: OS Independent
Classifier: Programming Language :: Python :: 3.11
Classifier: Programming Language :: Python :: 3.12
Classifier: Programming Language :: Python :: 3.13
Classifier: Programming Language :: Python :: 3.14
Requires-Dist: apscheduler>=3.10.4
Requires-Dist: beautifulsoup4[lxml]>=4.13.5
Requires-Dist: deluge-client>=1.10.2
Requires-Dist: fastapi>=0.122.0
Requires-Dist: aiohttp[speedups]>=3.13.2
Requires-Dist: humanfriendly>=10.0
Requires-Dist: msgspec[yaml]>=0.20.0
Requires-Dist: platformdirs>=4.4.0
Requires-Dist: qbittorrent-api>=2025.7.0
Requires-Dist: aiolimiter>=1.1.0
Requires-Dist: torf>=4.3.0
Requires-Dist: transmission-rpc>=7.0.11
Requires-Dist: uvicorn[standard]>=0.35.0
Requires-Dist: uvloop>=0.19.0 ; sys_platform != 'win32'
Requires-Dist: winloop>=0.1.0 ; sys_platform == 'win32'
Requires-Dist: reflink-copy>=0.3.2
Requires-Dist: sqlalchemy[aiosqlite]>=2.0.44
Requires-Dist: defusedxml>=0.7.1
Requires-Python: >=3.11
Project-URL: Documentation, https://github.com/KyokoMiki/nemorosa/wiki
Project-URL: Homepage, https://github.com/KyokoMiki/nemorosa
Project-URL: Issues, https://github.com/KyokoMiki/nemorosa/issues
Project-URL: Repository, https://github.com/KyokoMiki/nemorosa
